RTL/Synchronizer.v
//==========================================
// Function : Sincronizador de dois flip-flops (double flopping).
// Notes    : Usado para cruzar os ponteiros Gray entre os dominios
//            de WClk e RClk. Um par de FFs por bit de ponteiro.
//=========================================

`timescale 1ns/1ps

module Synchronizer
   #(parameter   SYNC_WIDTH = 5)
    (output reg  [SYNC_WIDTH-1:0]       Q_out,      //Saida sincronizada (2o flip-flop).
     input wire  [SYNC_WIDTH-1:0]       D_in,       //Entrada do outro dominio de clock.
     input wire                         Clear_in,   //Reset assincrono.
     input wire                         clk);       //Clock do dominio de destino.

    /////////Internal connections & variables///////
    reg    [SYNC_WIDTH-1:0]            Q_meta;     //Saida do 1o flip-flop (metaestavel).

    /////////Code///////////////////////
    always @ (posedge clk, posedge Clear_in)
        if (Clear_in) begin
            Q_meta <= {SYNC_WIDTH{1'b0}};
            Q_out  <= {SYNC_WIDTH{1'b0}};
        end
        else begin
            Q_meta <= D_in;      //1o flip-flop.
            Q_out  <= Q_meta;    //2o flip-flop (double flop resynchronization).
        end

endmodule

RTL/GrayCounter.v
//==========================================
// Function : Contador Gray/Binario para ponteiros de FIFO assincrona.
// Notes    : Versao convencional (Cummings). Mantem o contador binario
//            visivel (endereco da RAM) e disponibiliza o proximo valor
//            Gray de forma combinacional, permitindo que Full_out e
//            Empty_out sejam gerados em flip-flops (sem latches).
//            Clear_in e um reset assincrono.
//=========================================

`timescale 1ns/1ps

module GrayCounter
   #(parameter   COUNTER_WIDTH = 4)
    (output reg  [COUNTER_WIDTH-1:0]    GrayCount_out,    //Ponteiro em codigo Gray (registrado).
     output reg  [COUNTER_WIDTH-1:0]    BinaryCount_out,  //Ponteiro binario (endereco da RAM).
     output wire [COUNTER_WIDTH-1:0]    GrayNext_out,     //Proximo valor Gray (combinacional).
     output wire [COUNTER_WIDTH-1:0]    BinaryNext_out,   //Proximo valor binario (combinacional).
     input wire                         Enable_in,        //Habilita a contagem.
     input wire                         Clear_in,         //Reset assincrono.
     input wire                         clk);

    /////////Internal connections & variables///////
    wire   [COUNTER_WIDTH-1:0]         BinaryNext;

    /////////Code///////////////////////
    //Proximo ponteiro binario e sua conversao para Gray:
    assign BinaryNext     = BinaryCount_out + {{(COUNTER_WIDTH-1){1'b0}}, (Enable_in & ~Clear_in)};
    assign BinaryNext_out = BinaryNext;
    assign GrayNext_out   = BinaryNext ^ (BinaryNext >> 1);

    //Registradores dos ponteiros (reset assincrono, sem latches):
    always @ (posedge clk, posedge Clear_in)
        if (Clear_in) begin
            BinaryCount_out <= {COUNTER_WIDTH{1'b0}};
            GrayCount_out   <= {COUNTER_WIDTH{1'b0}};
        end
        else begin
            BinaryCount_out <= BinaryNext;
            GrayCount_out   <= GrayNext_out;
        end

endmodule

RTL/aFifo.v
//==========================================
// Function : Asynchronous FIFO (w/ 2 asynchronous clocks).
// Notes    : Versao convencional (Clifford E. Cummings, SNUG 2002)
//            com sincronizacao dos ponteiros Gray:
//              - ponteiros binarios e Gray com ADDRESS_WIDTH+1 bits;
//              - dois flip-flops de sincronizacao para cada ponteiro
//                que cruza dominio (double flop resynchronization);
//              - Full_out gerado somente no dominio de WClk;
//              - Empty_out gerado somente no dominio de RClk;
//              - nenhum latch inferido (toda logica de status e
//                registrada em flip-flops com reset assincrono).
//            A interface externa e identica a da FIFO original.
//=========================================

`timescale 1ns/1ps

module aFifo
  #(parameter    DATA_WIDTH    = 8,
                 ADDRESS_WIDTH = 4,
                 FIFO_DEPTH    = (1 << ADDRESS_WIDTH))
     //Reading port
    (output reg  [DATA_WIDTH-1:0]        Data_out,
     output reg                          Empty_out,
     input wire                          ReadEn_in,
     input wire                          RClk,
     //Writing port.
     input wire  [DATA_WIDTH-1:0]        Data_in,
     output reg                          Full_out,
     input wire                          WriteEn_in,
     input wire                          WClk,

     input wire                          Clear_in);

    /////Internal connections & variables//////
    localparam                          PTR_WIDTH = ADDRESS_WIDTH + 1;

    reg   [DATA_WIDTH-1:0]              Mem [FIFO_DEPTH-1:0];

    //Ponteiro de escrita (dominio WClk):
    wire  [PTR_WIDTH-1:0]               wGrayPtr, wBinPtr, wGrayNext, wBinNext;
    //Ponteiro de leitura (dominio RClk):
    wire  [PTR_WIDTH-1:0]               rGrayPtr, rBinPtr, rGrayNext, rBinNext;
    //Ponteiros apos o cruzamento de dominio (saida do 2o flip-flop):
    wire  [PTR_WIDTH-1:0]               rGrayPtr_wSync;  //rGrayPtr sincronizado em WClk.
    wire  [PTR_WIDTH-1:0]               wGrayPtr_rSync;  //wGrayPtr sincronizado em RClk.

    wire                                NextWriteAddressEn, NextReadAddressEn;
    wire                                FullNext, EmptyNext;

    //////////////Code///////////////
    //Fifo addresses support logic:
    //'Next Addresses' enable logic:
    assign NextWriteAddressEn = WriteEn_in & ~Full_out;
    assign NextReadAddressEn  = ReadEn_in  & ~Empty_out;

    //Data ports logic:
    //(Uses a dual-port RAM).
    //'Data_in' logic (dominio de WClk):
    always @ (posedge WClk)
        if (NextWriteAddressEn)
            Mem[wBinPtr[ADDRESS_WIDTH-1:0]] <= Data_in;

    //'Data_out' logic (dominio de RClk):
    always @ (posedge RClk)
        if (NextReadAddressEn)
            Data_out <= Mem[rBinPtr[ADDRESS_WIDTH-1:0]];

    //Addreses (Gray counters) logic - ADDRESS_WIDTH+1 bits:
    GrayCounter #(.COUNTER_WIDTH(PTR_WIDTH)) GrayCounter_pWr
       (.GrayCount_out(wGrayPtr),
        .BinaryCount_out(wBinPtr),
        .GrayNext_out(wGrayNext),
        .BinaryNext_out(wBinNext),
        .Enable_in(NextWriteAddressEn),
        .Clear_in(Clear_in),
        .clk(WClk)
       );

    GrayCounter #(.COUNTER_WIDTH(PTR_WIDTH)) GrayCounter_pRd
       (.GrayCount_out(rGrayPtr),
        .BinaryCount_out(rBinPtr),
        .GrayNext_out(rGrayNext),
        .BinaryNext_out(rBinNext),
        .Enable_in(NextReadAddressEn),
        .Clear_in(Clear_in),
        .clk(RClk)
       );

    //Cruzamento de dominio dos ponteiros Gray (dois flip-flops cada):
    //rGrayPtr (RClk) -> dominio de WClk:
    Synchronizer #(.SYNC_WIDTH(PTR_WIDTH)) Sync_rPtr_to_WClk
       (.Q_out(rGrayPtr_wSync),
        .D_in(rGrayPtr),
        .Clear_in(Clear_in),
        .clk(WClk)
       );

    //wGrayPtr (WClk) -> dominio de RClk:
    Synchronizer #(.SYNC_WIDTH(PTR_WIDTH)) Sync_wPtr_to_RClk
       (.Q_out(wGrayPtr_rSync),
        .D_in(wGrayPtr),
        .Clear_in(Clear_in),
        .clk(RClk)
       );

    //'Full_out' logic for the writing port (somente no dominio de WClk):
    //Cheia quando o proximo ponteiro Gray de escrita e igual ao ponteiro
    //Gray de leitura sincronizado com os dois MSBs invertidos.
    assign FullNext = (wGrayNext == {~rGrayPtr_wSync[PTR_WIDTH-1:PTR_WIDTH-2],
                                      rGrayPtr_wSync[PTR_WIDTH-3:0]});

    always @ (posedge WClk, posedge Clear_in)  //D Flip-Flop w/ Asynchronous Clear.
        if (Clear_in)
            Full_out <= 1'b0;
        else
            Full_out <= FullNext;

    //'Empty_out' logic for the reading port (somente no dominio de RClk):
    //Vazia quando o proximo ponteiro Gray de leitura alcanca o ponteiro
    //Gray de escrita sincronizado.
    assign EmptyNext = (rGrayNext == wGrayPtr_rSync);

    always @ (posedge RClk, posedge Clear_in)  //D Flip-Flop w/ Asynchronous Preset.
        if (Clear_in)
            Empty_out <= 1'b1;
        else
            Empty_out <= EmptyNext;

endmodule

RTL/aFifo_TB.v
//==========================================
// Testbench da FIFO assincrona (versao convencional).
// - DATA_WIDTH = 8, ADDRESS_WIDTH = 4 (16 posicoes).
// - Teste 1: preenche ate Full_out=1 e esvazia ate Empty_out=1.
// - Teste 2: escritas e leituras concorrentes, WClk=10ns / RClk=13ns,
//            com pelo menos 200 operacoes aceitas de cada tipo.
// - Teste 3: repete o teste concorrente invertendo os periodos.
// A sequencia de dados e um contador incremental (sequencia conhecida) e
// um placar de referencia detecta perda, duplicacao ou reordenacao.
// Todos os estimulos sao aplicados na borda de descida do clock do
// respectivo dominio, evitando condicoes de corrida com o DUT.
//=========================================

`timescale 1ns/1ps

module aFifo_TB
   #(parameter   DATA_WIDTH    = 8,
                 ADDRESS_WIDTH = 4,
                 FIFO_DEPTH    = (1 << ADDRESS_WIDTH));

     wire [DATA_WIDTH-1:0]        Data_out;
     wire                         Empty_out;
     reg                          ReadEn_in;
     reg                          RClk;
     //Writing port.
     reg  [DATA_WIDTH-1:0]        Data_in;
     wire                         Full_out;
     reg                          WriteEn_in;
     reg                          WClk;

     reg                          Clear_in;

    //Meio periodo de cada clock (programavel por teste):
    real                          WHalf = 5.0;    //WClk = 10,0 ns
    real                          RHalf = 6.5;    //RClk = 13,0 ns

    //Placar de referencia (modelo da fila):
    reg  [DATA_WIDTH-1:0]         RefQueue [0:8191];
    integer                       wr_idx, rd_idx;
    integer                       writes_ok, reads_ok, errors;

    // Disponibilizando o DUT(Device-Under-Test)
    aFifo #(.DATA_WIDTH(DATA_WIDTH), .ADDRESS_WIDTH(ADDRESS_WIDTH)) DUT (
        .Data_out(Data_out),
        .Empty_out(Empty_out),
        .ReadEn_in(ReadEn_in),
        .RClk(RClk),
        .Data_in(Data_in),
        .Full_out(Full_out),
        .WriteEn_in(WriteEn_in),
        .WClk(WClk),
        .Clear_in(Clear_in)
        );

    // Geracao dos dois clocks assincronos
    always #(WHalf) WClk = ~WClk;
    always #(RHalf) RClk = ~RClk;

    //---------------------------------------------------------
    // Modelo de referencia
    //---------------------------------------------------------
    // Escrita aceita (WriteEn_in && !Full_out): guarda o dado escrito e
    // avanca a sequencia conhecida de dados.
    always @ (posedge WClk)
        if (!Clear_in && WriteEn_in && !Full_out) begin
            RefQueue[wr_idx] = Data_in;
            wr_idx    = wr_idx + 1;
            writes_ok = writes_ok + 1;
            Data_in  <= Data_in + 1'b1;
        end

    // Leitura aceita (ReadEn_in && !Empty_out): Data_out e atualizado na
    // mesma borda; a comparacao e feita logo apos a atualizacao.
    always @ (posedge RClk)
        if (!Clear_in && ReadEn_in && !Empty_out) begin
            #0.5;
            if (Data_out !== RefQueue[rd_idx]) begin
                errors = errors + 1;
                $display("[%0t] ERRO na leitura %0d: Data_out=%0d, esperado=%0d",
                          $time, rd_idx, Data_out, RefQueue[rd_idx]);
            end
            else
                reads_ok = reads_ok + 1;
            rd_idx = rd_idx + 1;
        end

    //---------------------------------------------------------
    // Tarefas de teste
    //---------------------------------------------------------
    task do_reset;
        begin
            @(negedge WClk) WriteEn_in = 0;
            @(negedge RClk) ReadEn_in  = 0;
            Clear_in = 1;
            #50;
            @(negedge WClk) Clear_in = 0;
            wr_idx = 0; rd_idx = 0;
            #50;
        end
    endtask

    // Teste 1: preenche ate Full_out=1, depois esvazia ate Empty_out=1.
    task test_fill_then_drain;
        integer w0, r0;
        begin
            $display("\n--- Teste 1: preencher ate Full_out=1 e esvaziar ate Empty_out=1 ---");
            w0 = writes_ok; r0 = reads_ok;
            @(negedge WClk) WriteEn_in = 1;
            wait (Full_out === 1'b1);
            @(negedge WClk) WriteEn_in = 0;
            $display("[%0t] Full_out=1 apos %0d escritas aceitas (profundidade = %0d)",
                      $time, writes_ok - w0, FIFO_DEPTH);
            if ((writes_ok - w0) !== FIFO_DEPTH) begin
                errors = errors + 1;
                $display("ERRO: numero de escritas aceitas diferente da profundidade.");
            end

            #100;
            @(negedge RClk) ReadEn_in = 1;
            wait (Empty_out === 1'b1);
            @(negedge RClk) ReadEn_in = 0;
            $display("[%0t] Empty_out=1 apos %0d leituras corretas (erros acumulados = %0d)",
                      $time, reads_ok - r0, errors);
            if ((reads_ok - r0) !== FIFO_DEPTH) begin
                errors = errors + 1;
                $display("ERRO: numero de leituras diferente da profundidade.");
            end
            #100;
        end
    endtask

    // Testes 2 e 3: escritas e leituras concorrentes.
    task test_concurrent;
        input real wper;
        input real rper;
        input integer n_ops;
        integer w0, r0;
        begin
            $display("\n--- Teste concorrente: WClk = %0.1f ns, RClk = %0.1f ns, %0d operacoes ---",
                      wper, rper, n_ops);
            WHalf = wper/2.0;
            RHalf = rper/2.0;
            w0 = writes_ok;
            r0 = reads_ok;
            @(negedge WClk) WriteEn_in = 1;
            @(negedge RClk) ReadEn_in  = 1;
            wait (((writes_ok - w0) >= n_ops) && ((reads_ok - r0) >= n_ops));
            @(negedge WClk) WriteEn_in = 0;
            #200;
            @(negedge RClk) ReadEn_in = 0;   //drena o que restou na FIFO.
            #200;
            $display("[%0t] escritas aceitas = %0d, leituras corretas = %0d, erros = %0d",
                      $time, writes_ok - w0, reads_ok - r0, errors);
        end
    endtask

    //---------------------------------------------------------
    // Sequencia principal
    //---------------------------------------------------------
    initial begin
        WClk  = 0;
        RClk  = 0;
        Data_in    = 8'h00;
        ReadEn_in  = 0;
        WriteEn_in = 0;
        Clear_in   = 0;
        wr_idx = 0; rd_idx = 0;
        writes_ok = 0; reads_ok = 0; errors = 0;

        do_reset;
        test_fill_then_drain;                //WClk = 10 ns, RClk = 13 ns

        do_reset;
        test_concurrent(10.0, 13.0, 200);    //WClk mais rapido que RClk.

        do_reset;
        test_concurrent(13.0, 10.0, 200);    //periodos invertidos.

        $display("\n===== RESULTADO FINAL: %0d leituras verificadas, %0d erro(s) =====",
                  reads_ok, errors);
        if (errors == 0)
            $display("OK: sem perda, duplicacao ou reordenacao de dados.\n");
        else
            $display("FALHA: verificar as formas de onda em aFifo_TB.vcd\n");
        $finish;
    end

    initial begin
        $dumpfile("aFifo_TB.vcd");
        $dumpvars(0, aFifo_TB);
        #500000;
        $display("TIMEOUT");
        $finish;
    end

endmodule

RTL/aFifo_TB.vcd
$date
	Sat Sep 05 10:23:00 2026
$end
$version
	Icarus Verilog
$end
$timescale
	1ps
$end
$scope module aFifo_TB $end
$var wire 1 ! Full_out $end
$var wire 1 " Empty_out $end
$var wire 8 # Data_out [7:0] $end
$var parameter 32 $ ADDRESS_WIDTH $end
$var parameter 32 % DATA_WIDTH $end
$var parameter 36 & FIFO_DEPTH $end
$var reg 1 ' Clear_in $end
$var reg 8 ( Data_in [7:0] $end
$var reg 1 ) RClk $end
$var reg 1 * ReadEn_in $end
$var reg 1 + WClk $end
$var reg 1 , WriteEn_in $end
$var real 1 - RHalf $end
$var real 1 . WHalf $end
$var integer 32 / errors [31:0] $end
$var integer 32 0 rd_idx [31:0] $end
$var integer 32 1 reads_ok [31:0] $end
$var integer 32 2 wr_idx [31:0] $end
$var integer 32 3 writes_ok [31:0] $end
$scope module DUT $end
$var wire 1 ' Clear_in $end
$var wire 8 4 Data_in [7:0] $end
$var wire 1 5 NextReadAddressEn $end
$var wire 1 6 NextWriteAddressEn $end
$var wire 1 ) RClk $end
$var wire 1 * ReadEn_in $end
$var wire 1 + WClk $end
$var wire 1 , WriteEn_in $end
$var wire 5 7 wGrayPtr_rSync [4:0] $end
$var wire 5 8 wGrayPtr [4:0] $end
$var wire 5 9 wGrayNext [4:0] $end
$var wire 5 : wBinPtr [4:0] $end
$var wire 5 ; wBinNext [4:0] $end
$var wire 5 < rGrayPtr_wSync [4:0] $end
$var wire 5 = rGrayPtr [4:0] $end
$var wire 5 > rGrayNext [4:0] $end
$var wire 5 ? rBinPtr [4:0] $end
$var wire 5 @ rBinNext [4:0] $end
$var wire 1 A FullNext $end
$var wire 1 B EmptyNext $end
$var parameter 32 C ADDRESS_WIDTH $end
$var parameter 32 D DATA_WIDTH $end
$var parameter 36 E FIFO_DEPTH $end
$var parameter 33 F PTR_WIDTH $end
$var reg 8 G Data_out [7:0] $end
$var reg 1 " Empty_out $end
$var reg 1 ! Full_out $end
$scope module GrayCounter_pRd $end
$var wire 5 H BinaryNext_out [4:0] $end
$var wire 1 ' Clear_in $end
$var wire 1 5 Enable_in $end
$var wire 5 I GrayNext_out [4:0] $end
$var wire 1 ) clk $end
$var wire 5 J BinaryNext [4:0] $end
$var parameter 33 K COUNTER_WIDTH $end
$var reg 5 L BinaryCount_out [4:0] $end
$var reg 5 M GrayCount_out [4:0] $end
$upscope $end
$scope module GrayCounter_pWr $end
$var wire 5 N BinaryNext_out [4:0] $end
$var wire 1 ' Clear_in $end
$var wire 1 6 Enable_in $end
$var wire 5 O GrayNext_out [4:0] $end
$var wire 1 + clk $end
$var wire 5 P BinaryNext [4:0] $end
$var parameter 33 Q COUNTER_WIDTH $end
$var reg 5 R BinaryCount_out [4:0] $end
$var reg 5 S GrayCount_out [4:0] $end
$upscope $end
$scope module Sync_rPtr_to_WClk $end
$var wire 1 ' Clear_in $end
$var wire 5 T D_in [4:0] $end
$var wire 1 + clk $end
$var parameter 33 U SYNC_WIDTH $end
$var reg 5 V Q_meta [4:0] $end
$var reg 5 W Q_out [4:0] $end
$upscope $end
$scope module Sync_wPtr_to_RClk $end
$var wire 1 ' Clear_in $end
$var wire 5 X D_in [4:0] $end
$var wire 1 ) clk $end
$var parameter 33 Y SYNC_WIDTH $end
$var reg 5 Z Q_meta [4:0] $end
$var reg 5 [ Q_out [4:0] $end
$upscope $end
$upscope $end
$scope task do_reset $end
$upscope $end
$scope task test_concurrent $end
$var integer 32 \ n_ops [31:0] $end
$var integer 32 ] r0 [31:0] $end
$var real 1 ^ rper $end
$var integer 32 _ w0 [31:0] $end
$var real 1 ` wper $end
$upscope $end
$scope task test_fill_then_drain $end
$var integer 32 a r0 [31:0] $end
$var integer 32 b w0 [31:0] $end
$upscope $end
$upscope $end
$enddefinitions $end
$comment Show the parameter values. $end
$dumpall
b101 Y
b101 U
b101 Q
b101 K
b101 F
b10000 E
b1000 D
b100 C
b10000 &
b1000 %
b100 $
$end
#0
$dumpvars
bx b
bx a
r0 `
bx _
r0 ^
bx ]
bx \
bx [
bx Z
bx X
bx W
bx V
bx T
bx S
bx R
bx P
bx O
bx N
bx M
bx L
bx J
bx I
bx H
bx G
xB
xA
bx @
bx ?
bx >
bx =
bx <
bx ;
bx :
bx 9
bx 8
bx 7
06
05
b0 4
b0 3
b0 2
b0 1
b0 0
b0 /
r5 .
r6.5 -
0,
0+
0*
0)
b0 (
0'
bx #
x"
x!
$end
#5000
1+
#6500
1)
#10000
0+
#13000
1B
0A
b0 >
b0 I
b0 9
b0 O
1"
b0 7
b0 [
b0 Z
b0 =
b0 M
b0 T
b0 @
b0 H
b0 J
b0 ?
b0 L
0!
b0 <
b0 W
b0 V
b0 8
b0 S
b0 X
b0 ;
b0 N
b0 P
b0 :
b0 R
1'
0)
#15000
1+
#19500
1)
#20000
0+
#25000
1+
#26000
0)
#30000
0+
#32500
1)
#35000
1+
#39000
0)
#40000
0+
#45000
1+
#45500
1)
#50000
0+
#52000
0)
#55000
1+
#58500
1)
#60000
0+
#65000
1+
0)
#70000
0'
0+
#71500
1)
#75000
1+
#78000
0)
#80000
0+
#84500
1)
#85000
1+
#90000
0+
#91000
0)
#95000
1+
#97500
1)
#100000
0+
#104000
0)
#105000
1+
#110000
0+
#110500
1)
#115000
1+
#117000
0)
#120000
b1 9
b1 O
b1 ;
b1 N
b1 P
16
1,
0+
b0 a
b0 b
#123500
1)
#125000
b11 9
b11 O
b1 8
b1 S
b1 X
b10 ;
b10 N
b10 P
b1 :
b1 R
b1 (
b1 4
b1 3
b1 2
1+
#130000
0+
0)
#135000
b10 9
b10 O
b11 8
b11 S
b11 X
b11 ;
b11 N
b11 P
b10 :
b10 R
b10 (
b10 4
b10 3
b10 2
1+
#136500
b11 Z
1)
#140000
0+
#143000
0)
#145000
b110 9
b110 O
b10 8
b10 S
b10 X
b100 ;
b100 N
b100 P
b11 :
b11 R
b11 (
b11 4
b11 3
b11 2
1+
#149500
0B
b11 7
b11 [
b10 Z
1)
#150000
0+
#155000
b111 9
b111 O
b110 8
b110 S
b110 X
b101 ;
b101 N
b101 P
b100 :
b100 R
b100 (
b100 4
b100 3
b100 2
1+
#156000
0)
#160000
0+
#162500
0"
b10 7
b10 [
b110 Z
1)
#165000
b101 9
b101 O
b111 8
b111 S
b111 X
b110 ;
b110 N
b110 P
b101 :
b101 R
b101 (
b101 4
b101 3
b101 2
1+
#169000
0)
#170000
0+
#175000
b100 9
b100 O
b101 8
b101 S
b101 X
b111 ;
b111 N
b111 P
b110 :
b110 R
b110 (
b110 4
b110 3
b110 2
1+
#175500
b110 7
b110 [
b101 Z
1)
#180000
0+
#182000
0)
#185000
b1100 9
b1100 O
b100 8
b100 S
b100 X
b1000 ;
b1000 N
b1000 P
b111 :
b111 R
b111 (
b111 4
b111 3
b111 2
1+
#188500
b101 7
b101 [
b100 Z
1)
#190000
0+
#195000
b1101 9
b1101 O
b1100 8
b1100 S
b1100 X
b1001 ;
b1001 N
b1001 P
b1000 :
b1000 R
b1000 (
b1000 4
b1000 3
b1000 2
1+
0)
#200000
0+
#201500
b100 7
b100 [
b1100 Z
1)
#205000
b1111 9
b1111 O
b1101 8
b1101 S
b1101 X
b1010 ;
b1010 N
b1010 P
b1001 :
b1001 R
b1001 (
b1001 4
b1001 3
b1001 2
1+
#208000
0)
#210000
0+
#214500
b1100 7
b1100 [
b1101 Z
1)
#215000
b1110 9
b1110 O
b1111 8
b1111 S
b1111 X
b1011 ;
b1011 N
b1011 P
b1010 :
b1010 R
b1010 (
b1010 4
b1010 3
b1010 2
1+
#220000
0+
#221000
0)
#225000
b1010 9
b1010 O
b1110 8
b1110 S
b1110 X
b1100 ;
b1100 N
b1100 P
b1011 :
b1011 R
b1011 (
b1011 4
b1011 3
b1011 2
1+
#227500
b1101 7
b1101 [
b1110 Z
1)
#230000
0+
#234000
0)
#235000
b1011 9
b1011 O
b1010 8
b1010 S
b1010 X
b1101 ;
b1101 N
b1101 P
b1100 :
b1100 R
b1100 (
b1100 4
b1100 3
b1100 2
1+
#240000
0+
#240500
b1110 7
b1110 [
b1010 Z
1)
#245000
b1001 9
b1001 O
b1011 8
b1011 S
b1011 X
b1110 ;
b1110 N
b1110 P
b1101 :
b1101 R
b1101 (
b1101 4
b1101 3
b1101 2
1+
#247000
0)
#250000
0+
#253500
b1010 7
b1010 [
b1011 Z
1)
#255000
b1000 9
b1000 O
b1001 8
b1001 S
b1001 X
b1111 ;
b1111 N
b1111 P
b1110 :
b1110 R
b1110 (
b1110 4
b1110 3
b1110 2
1+
#260000
0+
0)
#265000
1A
b11000 9
b11000 O
b1000 8
b1000 S
b1000 X
b10000 ;
b10000 N
b10000 P
b1111 :
b1111 R
b1111 (
b1111 4
b1111 3
b1111 2
1+
#266500
b1011 7
b1011 [
b1000 Z
1)
#270000
0+
#273000
0)
#275000
06
1A
b11000 9
b11000 O
b11000 8
b11000 S
b11000 X
b10000 ;
b10000 N
b10000 P
b10000 :
b10000 R
1!
b10000 (
b10000 4
b10000 3
b10000 2
1+
#279500
b1000 7
b1000 [
b11000 Z
1)
#280000
0,
0+
#285000
1+
#286000
0)
#290000
0+
#292500
b11000 7
b11000 [
1)
#295000
1+
#299000
0)
#300000
0+
#305000
1+
#305500
1)
#310000
0+
#312000
0)
#315000
1+
#318500
1)
#320000
0+
#325000
1+
0)
#330000
0+
#331500
1)
#335000
1+
#338000
0)
#340000
0+
#344500
1)
#345000
1+
#350000
0+
#351000
0)
#355000
1+
#357500
1)
#360000
0+
#364000
0)
#365000
1+
#370000
0+
#370500
1)
#375000
1+
#377000
0)
#380000
0+
#383500
1)
#385000
1+
#390000
b1 >
b1 I
b1 @
b1 H
b1 J
15
1*
0+
0)
#395000
1+
#396500
b11 >
b11 I
b1 =
b1 M
b1 T
b10 @
b10 H
b10 J
b1 ?
b1 L
b0 #
b0 G
1)
#397000
b1 0
b1 1
#400000
0+
#403000
0)
#405000
b1 V
1+
#409500
b10 >
b10 I
b11 =
b11 M
b11 T
b11 @
b11 H
b11 J
b10 ?
b10 L
b1 #
b1 G
1)
#410000
b10 0
b10 1
0+
#415000
0A
b1 <
b1 W
b11 V
1+
#416000
0)
#420000
0+
#422500
b110 >
b110 I
b10 =
b10 M
b10 T
b100 @
b100 H
b100 J
b11 ?
b11 L
b10 #
b10 G
1)
#423000
b11 0
b11 1
#425000
0!
b11 <
b11 W
b10 V
1+
#429000
0)
#430000
0+
#435000
b10 <
b10 W
1+
#435500
b111 >
b111 I
b110 =
b110 M
b110 T
b101 @
b101 H
b101 J
b100 ?
b100 L
b11 #
b11 G
1)
#436000
b100 0
b100 1
#440000
0+
#442000
0)
#445000
b110 V
1+
#448500
b101 >
b101 I
b111 =
b111 M
b111 T
b110 @
b110 H
b110 J
b101 ?
b101 L
b100 #
b100 G
1)
#449000
b101 0
b101 1
#450000
0+
#455000
b110 <
b110 W
b111 V
1+
0)
#460000
0+
#461500
b100 >
b100 I
b101 =
b101 M
b101 T
b111 @
b111 H
b111 J
b110 ?
b110 L
b101 #
b101 G
1)
#462000
b110 0
b110 1
#465000
b111 <
b111 W
b101 V
1+
#468000
0)
#470000
0+
#474500
b1100 >
b1100 I
b100 =
b100 M
b100 T
b1000 @
b1000 H
b1000 J
b111 ?
b111 L
b110 #
b110 G
1)
#475000
b101 <
b101 W
b100 V
b111 0
b111 1
1+
#480000
0+
#481000
0)
#485000
b100 <
b100 W
1+
#487500
b1101 >
b1101 I
b1100 =
b1100 M
b1100 T
b1001 @
b1001 H
b1001 J
b1000 ?
b1000 L
b111 #
b111 G
1)
#488000
b1000 0
b1000 1
#490000
0+
#494000
0)
#495000
b1100 V
1+
#500000
0+
#500500
b1111 >
b1111 I
b1101 =
b1101 M
b1101 T
b1010 @
b1010 H
b1010 J
b1001 ?
b1001 L
b1000 #
b1000 G
1)
#501000
b1001 0
b1001 1
#505000
b1100 <
b1100 W
b1101 V
1+
#507000
0)
#510000
0+
#513500
b1110 >
b1110 I
b1111 =
b1111 M
b1111 T
b1011 @
b1011 H
b1011 J
b1010 ?
b1010 L
b1001 #
b1001 G
1)
#514000
b1010 0
b1010 1
#515000
b1101 <
b1101 W
b1111 V
1+
#520000
0+
0)
#525000
b1111 <
b1111 W
1+
#526500
b1010 >
b1010 I
b1110 =
b1110 M
b1110 T
b1100 @
b1100 H
b1100 J
b1011 ?
b1011 L
b1010 #
b1010 G
1)
#527000
b1011 0
b1011 1
#530000
0+
#533000
0)
#535000
b1110 V
1+
#539500
b1011 >
b1011 I
b1010 =
b1010 M
b1010 T
b1101 @
b1101 H
b1101 J
b1100 ?
b1100 L
b1011 #
b1011 G
1)
#540000
b1100 0
b1100 1
0+
#545000
b1110 <
b1110 W
b1010 V
1+
#546000
0)
#550000
0+
#552500
b1001 >
b1001 I
b1011 =
b1011 M
b1011 T
b1110 @
b1110 H
b1110 J
b1101 ?
b1101 L
b1100 #
b1100 G
1)
#553000
b1101 0
b1101 1
#555000
b1010 <
b1010 W
b1011 V
1+
#559000
0)
#560000
0+
#565000
b1011 <
b1011 W
1+
#565500
b1000 >
b1000 I
b1001 =
b1001 M
b1001 T
b1111 @
b1111 H
b1111 J
b1110 ?
b1110 L
b1101 #
b1101 G
1)
#566000
b1110 0
b1110 1
#570000
0+
#572000
0)
#575000
b1001 V
1+
#578500
1B
b11000 >
b11000 I
b1000 =
b1000 M
b1000 T
b10000 @
b10000 H
b10000 J
b1111 ?
b1111 L
b1110 #
b1110 G
1)
#579000
b1111 0
b1111 1
#580000
0+
#585000
b1001 <
b1001 W
b1000 V
1+
0)
#590000
0+
#591500
05
1B
b11000 >
b11000 I
b11000 =
b11000 M
b11000 T
b10000 @
b10000 H
b10000 J
b10000 ?
b10000 L
1"
b1111 #
b1111 G
1)
#592000
b10000 0
b10000 1
#595000
b1000 <
b1000 W
b11000 V
1+
#598000
0*
0)
#600000
0+
#604500
1)
#605000
b11000 <
b11000 W
1+
#610000
0+
#611000
0)
#615000
1+
#617500
1)
#620000
0+
#624000
0)
#625000
1+
#630000
0+
#630500
1)
#635000
1+
#637000
0)
#640000
0+
#643500
1)
#645000
1+
#650000
0+
0)
#655000
1+
#656500
1)
#660000
0+
#663000
0)
#665000
1+
#669500
1)
#670000
0+
#675000
1+
#676000
0)
#680000
0+
#682500
1)
#685000
1+
#689000
0)
#690000
0+
#695000
1+
#695500
1)
#700000
0+
#702000
0A
b0 >
b0 I
b0 9
b0 O
1B
b0 7
b0 [
b0 Z
b0 =
b0 M
b0 T
b0 @
b0 H
b0 J
b0 ?
b0 L
b0 <
b0 W
b0 V
b0 8
b0 S
b0 X
b0 ;
b0 N
b0 P
b0 :
b0 R
1'
0)
#705000
1+
#708500
1)
#710000
0+
#715000
1+
0)
#720000
0+
#721500
1)
#725000
1+
#728000
0)
#730000
0+
#734500
1)
#735000
1+
#740000
0+
#741000
0)
#745000
1+
#747500
1)
#750000
0+
#754000
0)
#755000
1+
#760000
b0 0
b0 2
0'
0+
#760500
1)
#765000
1+
#767000
0)
#770000
0+
#773500
1)
#775000
1+
#780000
0+
0)
#785000
1+
#786500
1)
#790000
0+
#793000
0)
#795000
1+
#799500
1)
#800000
0+
#805000
1+
#806000
0)
#810000
b1 9
b1 O
b1 ;
b1 N
b1 P
16
1,
0+
b10000 ]
b10000 _
b11001000 \
r13 ^
r10 `
#812500
1)
#815000
b11 9
b11 O
b1 8
b1 S
b1 X
b10 ;
b10 N
b10 P
b1 :
b1 R
b10001 (
b10001 4
b10001 3
b1 2
1+
#819000
1*
0)
#820000
0+
#825000
b10 9
b10 O
b11 8
b11 S
b11 X
b11 ;
b11 N
b11 P
b10 :
b10 R
b10010 (
b10010 4
b10010 3
b10 2
1+
#825500
b11 Z
1)
#830000
0+
#832000
0)
#835000
b110 9
b110 O
b10 8
b10 S
b10 X
b100 ;
b100 N
b100 P
b11 :
b11 R
b10011 (
b10011 4
b10011 3
b11 2
1+
#838500
0B
b11 7
b11 [
b10 Z
1)
#840000
0+
